apple_health_parser/__init__.py
apple_health_parser/config/__init__.py
apple_health_parser/config/definitions.py
apple_health_parser/config/flags.yaml
apple_health_parser/consts.py
apple_health_parser/decorators.py
apple_health_parser/exceptions.py
apple_health_parser/interfaces/__init__.py
apple_health_parser/interfaces/plot_interface.py
apple_health_parser/interfaces/preprocessor_interface.py
apple_health_parser/models/__init__.py
apple_health_parser/models/parsed.py
apple_health_parser/models/records.py
apple_health_parser/plot/__init__.py
apple_health_parser/plot/overviews.py
apple_health_parser/plot/plots.py
apple_health_parser/plot/sleep.py
apple_health_parser/py.typed
apple_health_parser/scripts/__init__.py
apple_health_parser/scripts/main.py
apple_health_parser/utils/__init__.py
apple_health_parser/utils/loader.py
apple_health_parser/utils/logging.py
apple_health_parser/utils/parser.py
apple_health_parser/utils/preprocessor.py
apple_health_parser-1.1.5.dist-info/METADATA
apple_health_parser-1.1.5.dist-info/WHEEL
apple_health_parser-1.1.5.dist-info/entry_points.txt
apple_health_parser-1.1.5.dist-info/licenses/LICENSE
apple_health_parser-1.1.5.dist-info/RECORD
