Metadata-Version: 2.4
Name: apple-health-parser
Version: 1.1.5
Summary: Python package to parse, analyse, and plot Apple HealthKit data
License: MIT
License-File: LICENSE
Author: Alexandre Cirilo
Author-email: 38657258+alxdrcirilo@users.noreply.github.com
Requires-Python: >=3.11,<4.0
Classifier: License :: OSI Approved :: MIT License
Classifier: Programming Language :: Python :: 3
Classifier: Programming Language :: Python :: 3.11
Classifier: Programming Language :: Python :: 3.12
Classifier: Programming Language :: Python :: 3.13
Classifier: Programming Language :: Python :: 3.14
Requires-Dist: click (>=8.1.7,<9.0.0)
Requires-Dist: kaleido (==0.2.1)
Requires-Dist: pandas (>=2.2.2,<3.0.0)
Requires-Dist: plotly (>=5.22.0,<6.0.0)
Requires-Dist: pydantic (>=2.7.1,<3.0.0)
Requires-Dist: pydantic-extra-types (>=2.10.5,<3.0.0)
Requires-Dist: pyyaml (>=6.0.1,<7.0.0)
Project-URL: Repository, https://github.com/alxdrcirilo/apple-health-parser
